typed_requests/__init__.py
typed_requests/core.py
typed_requests/logger.py
typed_requests/py.typed
typed_requests/tls.py
divine_typed_requests-0.1.32.dist-info/METADATA
divine_typed_requests-0.1.32.dist-info/WHEEL
divine_typed_requests-0.1.32.dist-info/licenses/LICENSE
divine_typed_requests-0.1.32.dist-info/RECORD
