Metadata-Version: 2.4
Name: divine-typed-requests
Version: 0.1.32
Summary: A type-safe HTTP client library with validation and detailed error reporting.
Project-URL: Homepage, https://github.com/divinescreener/typed-requests
Project-URL: Issues, https://github.com/divinescreener/typed-requests/issues
Author-email: DIVINE <admin@divine.sh>
License: MIT
License-File: LICENSE
Requires-Python: >=3.13
Requires-Dist: divine-type-enforcer>=0.1.13
Requires-Dist: httpx[http2]>=0.28.1
